a3py/__init__.py
a3py/improved/__init__.py
a3py/improved/json.py
a3py/improved/readable.py
a3py/practical/__init__.py
a3py/practical/concurrence.py
a3py/practical/dynamic.py
a3py/practical/signal.py
a3py/practical/singleton_meta.py
a3py/simplified/__init__.py
a3py/simplified/case.py
a3py/simplified/datetime.py
a3py/simplified/env.py
a3py/simplified/hashlib.py
a3py-0.3.0.dist-info/LICENSE
a3py-0.3.0.dist-info/METADATA
a3py-0.3.0.dist-info/WHEEL
a3py-0.3.0.dist-info/top_level.txt
a3py-0.3.0.dist-info/RECORD
